NRandom/NRandom.py
NRandom/__init__.py
NRandom-2.0.dist-info/LICENSE.txt
NRandom-2.0.dist-info/METADATA
NRandom-2.0.dist-info/WHEEL
NRandom-2.0.dist-info/top_level.txt
NRandom-2.0.dist-info/RECORD
